cmft/__init__.py
cmft/__main__.py
cmft/extract_from_python.py
cmft/extract_message.py
cmft/utils.py
cmft-0.1.0.dist-info/entry_points.txt
cmft-0.1.0.dist-info/LICENSE
cmft-0.1.0.dist-info/WHEEL
cmft-0.1.0.dist-info/METADATA
cmft-0.1.0.dist-info/RECORD
