Metadata-Version: 2.1
Name: cmft
Version: 0.1.0
Summary: 
Home-page: https://github.com/dryobates/commit-message-from-test
License: MIT
Author: dryobates
Author-email: jakub.stolarski@gmail.com
Requires-Python: >=3.6,<4.0
Classifier: Development Status :: 1 - Planning
Classifier: Intended Audience :: Developers
Classifier: License :: OSI Approved :: MIT License
Classifier: Natural Language :: English
Classifier: Operating System :: OS Independent
Classifier: Programming Language :: Python :: 3
Classifier: Programming Language :: Python :: 3.6
Classifier: Programming Language :: Python :: 3.7
Classifier: Topic :: Software Development
Project-URL: Repository, https://github.com/dryobates/commit-message-from-test
